fl_manager/utils/nvflare_extensions/__init__.py
fl_manager/utils/nvflare_extensions/py.typed
fl_manager/utils/nvflare_extensions/nv/__init__.py
fl_manager/utils/nvflare_extensions/nv/executors/__init__.py
fl_manager/utils/nvflare_extensions/nv/executors/base_weight_initializer_executor.py
fl_manager/utils/nvflare_extensions/nv/workflows/__init__.py
fl_manager/utils/nvflare_extensions/nv/workflows/base_controller.py
fl_manager/utils/nvflare_extensions/nv/workflows/base_controller_with_client_selection.py
fl_manager/utils/nvflare_extensions/nv/workflows/model_export_controller.py
fl_manager/utils/nvflare_extensions/nv/workflows/pfl_model_export_controller.py
fl_manager/utils/nvflare_extensions/pt/__init__.py
fl_manager/utils/nvflare_extensions/pt/executors/__init__.py
fl_manager/utils/nvflare_extensions/pt/executors/pt_weight_initializer_executor.py
fl_manager_utils_nvflare_extensions-0.1.0.dist-info/METADATA
fl_manager_utils_nvflare_extensions-0.1.0.dist-info/WHEEL
fl_manager_utils_nvflare_extensions-0.1.0.dist-info/licenses/LICENSE
fl_manager_utils_nvflare_extensions-0.1.0.dist-info/RECORD
